cloudprice/__init__.py
cloudprice/azure.py
cloudprice/azure_helpers.py
cloudprice/prices.py
cloudprice/constants/__init__.py
cloudprice/constants/azure.py
cloudprice-0.0.3.dist-info/LICENSE.txt
cloudprice-0.0.3.dist-info/METADATA
cloudprice-0.0.3.dist-info/WHEEL
cloudprice-0.0.3.dist-info/top_level.txt
cloudprice-0.0.3.dist-info/RECORD
