Metadata-Version: 2.1
Name: cloudprice
Version: 0.0.3
Summary: A SDK for cloud compute pricing
Home-page: https://github.com/guanjieshen/cloud-compute-pricing
Author: Guanjie Shen
License: MIT License
Platform: UNKNOWN
Classifier: Development Status :: 3 - Alpha
Classifier: Intended Audience :: Developers
Classifier: Natural Language :: English
Classifier: License :: OSI Approved :: MIT License
Classifier: Programming Language :: Python :: 3.8
License-File: LICENSE.txt
Requires-Dist: requests (<3.0.0,>=2.5.0)
